grheat/__init__.py
grheat/absorber.py
grheat/exp_source.py
grheat/line_source.py
grheat/plane_source.py
grheat/point_source.py
grheat-0.2.1.dist-info/LICENSE.txt
grheat-0.2.1.dist-info/METADATA
grheat-0.2.1.dist-info/WHEEL
grheat-0.2.1.dist-info/top_level.txt
grheat-0.2.1.dist-info/RECORD
