Metadata-Version: 2.1
Name: grheat
Version: 0.2.1
Summary: Green's functions for point, line, and planar heat sources.
Home-page: https://github.com/scottprahl/grheat
Author: Scott Prahl
Author-email: scott.prahl@oit.edu
License: MIT
Keywords: temperature,heat transfer,Green's function,point source,line source,plane source
Classifier: Development Status :: 3 - Alpha
Classifier: License :: OSI Approved :: MIT License
Classifier: Intended Audience :: Science/Research
Classifier: Topic :: Scientific/Engineering :: Physics
Classifier: Programming Language :: Python
Classifier: Programming Language :: Python :: 3
Classifier: Programming Language :: Python :: 3.8
Classifier: Programming Language :: Python :: 3.9
Classifier: Programming Language :: Python :: 3.10
Classifier: Programming Language :: Python :: 3.11
Requires-Python: >=3.8
License-File: LICENSE.txt
Requires-Dist: numpy
Requires-Dist: matplotlib
Requires-Dist: scipy
